docs/source/__init__.py
docs/source/conf.py
pyzipcodeapi/__init__.py
pyzipcodeapi/api.py
pyzipcodeapi/dataclass.py
pyzipcodeapi/enums.py
pyzipcodeapi/example.py
pyzipcodeapi-2.0.0.dist-info/LICENSE.md
pyzipcodeapi-2.0.0.dist-info/METADATA
pyzipcodeapi-2.0.0.dist-info/WHEEL
pyzipcodeapi-2.0.0.dist-info/top_level.txt
pyzipcodeapi-2.0.0.dist-info/RECORD
