Metadata-Version: 2.1
Name: pyzipcodeapi
Version: 2.0.0
Summary: Py ZipCodeApi will make it easier for you to use the different options in ZipCodeAPI
Home-page: https://github.com/medbenmakhlouf/pyzipcodeapi
Download-URL: https://github.com/medbenmakhlouf/pyzipcodeapi/tarball/2.0.0
Author: Mohamed Ben Makhlouf
Author-email: med.b.makhlouf@gmail.com
License: BSD
Keywords: api,zipcode
Classifier: Intended Audience :: Developers
Classifier: Programming Language :: Python :: 3.10
License-File: LICENSE.md
